http_handler.py
http_handler_js.py
mediacrop.py
utils.py
mediacrop-4.0.0.dist-info/licenses/LICENSE
mediacrop-4.0.0.dist-info/METADATA
mediacrop-4.0.0.dist-info/WHEEL
mediacrop-4.0.0.dist-info/entry_points.txt
mediacrop-4.0.0.dist-info/top_level.txt
mediacrop-4.0.0.dist-info/RECORD
