Metadata-Version: 2.4
Name: mediacrop
Version: 4.0.0
Summary: A CLI tool for visually determining FFmpeg crop coordinates.
Home-page: https://github.com/mallikmusaddiq1/mediacrop
Author: Mallik Mohammad Musaddiq
Author-email: mallikmusaddiq1@gmail.com
License: MIT
Classifier: Development Status :: 5 - Production/Stable
Classifier: Environment :: Console
Classifier: Intended Audience :: End Users/Desktop
Classifier: License :: OSI Approved :: MIT License
Classifier: Operating System :: OS Independent
Classifier: Programming Language :: Python :: 3
Classifier: Topic :: Multimedia :: Video
Classifier: Topic :: Multimedia :: Graphics :: Editors
Classifier: Topic :: Utilities
Requires-Python: >=3.7
License-File: LICENSE
Dynamic: author
Dynamic: author-email
Dynamic: classifier
Dynamic: description
Dynamic: description-content-type
Dynamic: home-page
Dynamic: license
Dynamic: license-file
Dynamic: requires-python
Dynamic: summary
